pyChatGPT/Auth0.py
pyChatGPT/__init__.py
pyChatGPT/__main__.py
pyChatGPT/pyChatGPT.py
pyChatGPT-0.4.3.3.dist-info/LICENSE
pyChatGPT-0.4.3.3.dist-info/METADATA
pyChatGPT-0.4.3.3.dist-info/WHEEL
pyChatGPT-0.4.3.3.dist-info/top_level.txt
pyChatGPT-0.4.3.3.dist-info/RECORD
