Metadata-Version: 2.1
Name: pyChatGPT
Version: 0.4.3.3
Summary: An unofficial Python wrapper for OpenAI's ChatGPT API
Author-email: terry3041 <s71czbem@duck.com>
Project-URL: Homepage, https://github.com/terry3041/pyChatGPT
Project-URL: Bug Tracker, https://github.com/terry3041/pyChatGPT/issues
Classifier: Programming Language :: Python :: 3
Classifier: License :: OSI Approved :: GNU General Public License v3 (GPLv3)
Classifier: Operating System :: OS Independent
Requires-Python: >=3.7
License-File: LICENSE
